blis_cli/__init__.py
blis_cli/blis.py
blis_cli/commands/__init__.py
blis_cli/commands/docker.py
blis_cli/commands/domain.py
blis_cli/commands/install.py
blis_cli/commands/logs.py
blis_cli/commands/start.py
blis_cli/commands/status.py
blis_cli/commands/stop.py
blis_cli/commands/swap.py
blis_cli/commands/update.py
blis_cli/extra/001-blis_revamp.sql
blis_cli/extra/002-blis_127.sql
blis_cli/extra/003-blis_revamp-seed.sql
blis_cli/extra/004-blis_127-seed.sql
blis_cli/extra/docker-compose.yml
blis_cli/extra/templates/Caddyfile.j2
blis_cli/util/__init__.py
blis_cli/util/bash.py
blis_cli/util/caddy.py
blis_cli/util/config.py
blis_cli/util/docker_util.py
blis_cli/util/environment.py
blis_cli/util/packages.py
blis_cloud_cli-0.3.0.dist-info/METADATA
blis_cloud_cli-0.3.0.dist-info/WHEEL
blis_cloud_cli-0.3.0.dist-info/entry_points.txt
blis_cloud_cli-0.3.0.dist-info/licenses/LICENSE
blis_cloud_cli-0.3.0.dist-info/RECORD
